dorianUtils/Simulators.py
dorianUtils/VersionsManager.py
dorianUtils/__init__.py
dorianUtils/comUtils.py
dorianUtils/configFilesD.py
dorianUtils/fitUtils.py
dorianUtils/mplExtended.py
dorianUtils/utilsD.py
dorianUtils/assets/styles.css
dorianUtils/conf/colormaps.pkl
dorianUtils/conf/logo_sylfen.png
dorianUtils/conf/palettes.pkl
dorianUtils/conf/units.csv
dorianUtils-6.4.1.dist-info/METADATA
dorianUtils-6.4.1.dist-info/WHEEL
dorianUtils-6.4.1.dist-info/top_level.txt
dorianUtils-6.4.1.dist-info/RECORD
